genaibook/__init__.py
genaibook/_modidx.py
genaibook/core.py
genaibook-0.1.1.dist-info/LICENSE
genaibook-0.1.1.dist-info/METADATA
genaibook-0.1.1.dist-info/WHEEL
genaibook-0.1.1.dist-info/entry_points.txt
genaibook-0.1.1.dist-info/top_level.txt
genaibook-0.1.1.dist-info/RECORD
