Metadata-Version: 2.1
Name: genaibook
Version: 0.1.1
Summary: Utilities for 'Hands-On Generative AI with Transformers and Diffusion Models' (upcoming)
Home-page: https://github.com/genaibook/genaibook
Author: Jonathan Whitaker
Author-email: johnowhitaker@gmail.com
License: Apache Software License 2.0
Keywords: nbdev jupyter notebook python
Classifier: Development Status :: 4 - Beta
Classifier: Intended Audience :: Developers
Classifier: Natural Language :: English
Classifier: Programming Language :: Python :: 3.10
Classifier: License :: OSI Approved :: Apache Software License
Requires-Python: >=3.10
License-File: LICENSE
Requires-Dist: accelerate
Requires-Dist: sentencepiece
Requires-Dist: fastcore
Requires-Dist: pandas
Requires-Dist: torch
Requires-Dist: torchvision
Requires-Dist: torchaudio
Requires-Dist: torchsummary
Requires-Dist: pillow
Requires-Dist: matplotlib
Requires-Dist: numpy
Requires-Dist: scipy
Requires-Dist: librosa
Requires-Dist: diffusers
Requires-Dist: transformers
Requires-Dist: sentence-transformers
Requires-Dist: bitsandbytes
Requires-Dist: datasets[audio]
Requires-Dist: jiwer
Requires-Dist: evaluate
Requires-Dist: pydub
Requires-Dist: compel
Requires-Dist: mediapipe
Requires-Dist: controlnet-aux
Requires-Dist: peft
Provides-Extra: dev
